django_o365mail/__init__.py
django_o365mail/__version__.py
django_o365mail/backend.py
django_o365mail/file_base.py
django_o365mail/file_mimebase.py
django_o365mail/file_tuple.py
django_o365mail/o365_logger.py
django_o365mail/settings.py
django_o365mail/util.py
django_o365mail-1.1.0.dist-info/LICENSE
django_o365mail-1.1.0.dist-info/METADATA
django_o365mail-1.1.0.dist-info/WHEEL
django_o365mail-1.1.0.dist-info/top_level.txt
django_o365mail-1.1.0.dist-info/RECORD
