Metadata-Version: 2.1
Name: django-o365mail
Version: 1.1.0
Summary: Office 365 (O365) email backend for Django
Home-page: https://github.com/evyd13/django-o365mail
Author: Evelien Dekkers
Author-email: sixmoonskies@gmail.com
Project-URL: Bug Tracker, https://github.com/evyd13/django-o365mail/issues
Classifier: Programming Language :: Python :: 3
Classifier: License :: OSI Approved :: MIT License
Classifier: Operating System :: OS Independent
Classifier: Development Status :: 5 - Production/Stable
Classifier: Topic :: Communications :: Email
Classifier: Framework :: Django :: 2.2
Classifier: Framework :: Django :: 3.0
Classifier: Framework :: Django :: 3.1
Classifier: Framework :: Django :: 3.2
Classifier: Framework :: Django :: 4.0
Requires-Python: >=3.6
License-File: LICENSE
Requires-Dist: O365
